celery_prometheus/__init__.py
celery_prometheus/prometheus_bootstep.py
celery_prometheus/py.typed
celery_prometheus-1.1.0.dist-info/LICENSE
celery_prometheus-1.1.0.dist-info/METADATA
celery_prometheus-1.1.0.dist-info/WHEEL
celery_prometheus-1.1.0.dist-info/RECORD
