Metadata-Version: 2.1
Name: celery-prometheus
Version: 1.1.0
Summary: Celery with your own prometheus metrics
License: BSD-Derived
Author: Guillaume Gauvrit
Author-email: guillaume@gandi.net
Requires-Python: >=3.7,<4.0
Classifier: License :: Other/Proprietary License
Classifier: Programming Language :: Python :: 3
Classifier: Programming Language :: Python :: 3.7
Classifier: Programming Language :: Python :: 3.8
Classifier: Programming Language :: Python :: 3.9
Classifier: Programming Language :: Python :: 3.10
Classifier: Programming Language :: Python :: 3.11
Classifier: Programming Language :: Python :: 3.12
Requires-Dist: celery (>=4)
